beanhub_import/__init__.py
beanhub_import/constants.py
beanhub_import/data_types.py
beanhub_import/post_processor.py
beanhub_import/processor.py
beanhub_import/templates.py
beanhub_import-1.3.0.dist-info/METADATA
beanhub_import-1.3.0.dist-info/WHEEL
beanhub_import-1.3.0.dist-info/licenses/LICENSE
beanhub_import-1.3.0.dist-info/RECORD
