Metadata-Version: 2.4
Name: beanhub-import
Version: 1.3.0
Summary: The simple library for import extracted transactions provided by beanhub-extract and generate corresponding Beancount transactions based on predefined rules
Project-URL: Documentation, https://beanhub-import-docs.beanhub.io
Author-email: Fang-Pen Lin <fangpen@launchplatform.com>
License-Expression: MIT
License-File: LICENSE
Requires-Python: ~=3.9
Requires-Dist: beancount-black<1.1.0,>=1.0.2
Requires-Dist: beancount-parser<1.3.0,>=1.2.3
Requires-Dist: beanhub-extract<0.2.0,>=0.1.7
Requires-Dist: jinja2<4,>=3.1.5
Requires-Dist: pydantic<3.0.0,>=2.0.0
Requires-Dist: pytz<2025,>=2023.1
Requires-Dist: pyyaml<7,>=6.0.1
